{
  "languages": {
    "Go": 25
  },
  "frameworks": {},
  "namingPatterns": {
    "PascalCase": 84,
    "camelCase": 322,
    "snake_case": 50
  },
  "fileExtensions": {
    ".gitignore": 1,
    ".go": 25,
    ".json": 1,
    ".md": 298,
    ".yml": 1
  },
  "projectStructure": {},
  "importPatterns": {
    "style": "absolute",
    "aliasing": {},
    "barrelFiles": null,
    "defaultImports": 0,
    "namedImports": 2,
    "examples": []
  },
  "codeStyle": {
    "indentStyle": "tabs",
    "indentSize": 4,
    "quoteStyle": "",
    "semicolons": "optional",
    "lineEnding": "lf",
    "trailingComma": ""
  }
}